packspec/VERSION
packspec/__init__.py
packspec/cli.py
packspec-0.4.0.dist-info/DESCRIPTION.rst
packspec-0.4.0.dist-info/METADATA
packspec-0.4.0.dist-info/RECORD
packspec-0.4.0.dist-info/WHEEL
packspec-0.4.0.dist-info/entry_points.txt
packspec-0.4.0.dist-info/metadata.json
packspec-0.4.0.dist-info/top_level.txt
