Metadata-Version: 2.0
Name: packspec
Version: 0.4.0
Summary: Cross-language testings made easy: unified YML-based package specification and Python/JavaScript/Ruby/PHP test runners
Home-page: https://github.com/packspec/packspec-py
Author: Evgeny Karev
Author-email: eskarev@gmail.com
License: MIT
Keywords: packspec
Platform: UNKNOWN
Classifier: Development Status :: 4 - Beta
Classifier: Environment :: Web Environment
Classifier: Intended Audience :: Developers
Classifier: License :: OSI Approved :: MIT License
Classifier: Operating System :: OS Independent
Classifier: Programming Language :: Python :: 2
Classifier: Programming Language :: Python :: 2.7
Classifier: Programming Language :: Python :: 3
Classifier: Programming Language :: Python :: 3.3
Classifier: Programming Language :: Python :: 3.4
Classifier: Programming Language :: Python :: 3.5
Classifier: Topic :: Internet :: WWW/HTTP :: Dynamic Content
Classifier: Topic :: Software Development :: Libraries :: Python Modules
Requires-Dist: click (>=6.0,<7.0)
Requires-Dist: emoji (>=0.4,<1.0)
Requires-Dist: pyyaml (>=3.1,<4.0)
Requires-Dist: six (>=1.9,<2.0)
Provides-Extra: develop
Requires-Dist: pylama; extra == 'develop'
Requires-Dist: tox; extra == 'develop'
